sqlite2pg/__init__.py
sqlite2pg/cli.py
sqlite2pg/commands/config.py
sqlite2pg/commands/migrate.py
sqlite2pg/commands/schema.py
sqlite2pg/modules/__init__.py
sqlite2pg/modules/errors.py
sqlite2pg/modules/logging.py
sqlite2pg/modules/postgres.py
sqlite2pg/modules/sqlite.py
sqlite2pg/modules/worker.py
sqlite2pg/py.typed
sqlite2pg-0.1.4.dist-info/entry_points.txt
sqlite2pg-0.1.4.dist-info/LICENSE
sqlite2pg-0.1.4.dist-info/WHEEL
sqlite2pg-0.1.4.dist-info/METADATA
sqlite2pg-0.1.4.dist-info/RECORD
